lineartree/__init__.py
lineartree/_classes.py
lineartree/_criterion.py
lineartree/lineartree.py
linear_tree-0.3.5.dist-info/LICENSE
linear_tree-0.3.5.dist-info/METADATA
linear_tree-0.3.5.dist-info/WHEEL
linear_tree-0.3.5.dist-info/top_level.txt
linear_tree-0.3.5.dist-info/RECORD
