Metadata-Version: 2.1
Name: linear-tree
Version: 0.3.5
Summary: A python library to build Model Trees with Linear Models at the leaves.
Home-page: https://github.com/cerlymarco/linear-tree
Author: Marco Cerliani
Author-email: cerlymarco@gmail.com
License: MIT
Platform: UNKNOWN
Requires-Python: >=3
Requires-Dist: scikit-learn (>=0.24.2)
Requires-Dist: numpy
Requires-Dist: scipy
